adafruit_il0373.py
adafruit_circuitpython_il0373-2.0.3.dist-info/licenses/LICENSE
adafruit_circuitpython_il0373-2.0.3.dist-info/METADATA
adafruit_circuitpython_il0373-2.0.3.dist-info/WHEEL
adafruit_circuitpython_il0373-2.0.3.dist-info/top_level.txt
adafruit_circuitpython_il0373-2.0.3.dist-info/RECORD
